<?xml version="1.0" encoding="utf-8"?>
<LOCALIZATION>
	<!-- Localization information to credit the person who did this localization. -->
	<STRING key="LOCALIZED_BY"><![CDATA[Localized by sumomole - 2013]]></STRING>
	<STRING key="LOCALIZATION_VERSION"><![CDATA[中文（简体） v1.3.0.0]]></STRING>
	<!-- Strings for Main Window -->
	<STRING key="MISSING_DOTP_DIRECTORY_TITLE"><![CDATA[万智牌2014游戏目录未设置。]]></STRING>
	<STRING key="MISSING_DOTP_DIRECTORY_MESSAGE"><![CDATA[万智牌2014的游戏根目录还未设置，请现在完成设置。]]></STRING>
	<!-- Strings for the Menus -->
	<STRING key="MENU_FILE"><![CDATA[&文件]]></STRING>
	<STRING key="MENU_FILE_NEW"><![CDATA[&新套牌 ...]]></STRING>
	<STRING key="MENU_FILE_CREATE_FROM_EXISTING"><![CDATA[&在现有的套牌上创建 ...]]></STRING>
	<STRING key="MENU_FILE_OPEN"><![CDATA[&打开套牌 ...]]></STRING>
	<STRING key="MENU_FILE_SAVE"><![CDATA[&保存套牌]]></STRING>
	<STRING key="MENU_FILE_SAVE_AS"><![CDATA[&套牌另存为 ...]]></STRING>
	<STRING key="MENU_FILE_EXPORT"><![CDATA[&导出到 ...]]></STRING>
	<STRING key="MENU_FILE_EXPORT_DIRECTORY"><![CDATA[&目录]]></STRING>
	<STRING key="MENU_FILE_EXPORT_WAD"><![CDATA[&WAD文件]]></STRING>
	<STRING key="MENU_FILE_EXIT"><![CDATA[&退出]]></STRING>
	<STRING key="MENU_TOOLS"><![CDATA[&工具]]></STRING>
	<STRING key="MENU_TOOLS_REFRESH"><![CDATA[&刷新]]></STRING>
	<STRING key="MENU_TOOLS_SETUP_CUSTOM_DATA_FOLDER"><![CDATA[&设置自定义数据文件夹]]></STRING>
	<STRING key="MENU_TOOLS_CREATE_CORE_WAD"><![CDATA[&从自定义数据文件夹创建核心WAD文件 ...]]></STRING>
	<STRING key="MENU_TOOLS_OPTIONS"><![CDATA[&选项]]></STRING>
	<STRING key="MENU_ABOUT"><![CDATA[&关于]]></STRING>
	<STRING key="MENU_EXPORT_IMAGE"><![CDATA[&导出此牌的预览图]]></STRING>
	<STRING key="MENU_EXPORT_CARD_PREVIEWS"><![CDATA[&导出此牌的预览图]]></STRING>
	<STRING key="MENU_EXPORT_CARD_XML"><![CDATA[&导出此牌的文件]]></STRING>
	<STRING key="MENU_EXPORT_IMAGE_CROP"><![CDATA[&导出此牌的插图]]></STRING>
	<!-- Strings for the Card Listing Columns -->
	<STRING key="COLUMN_TEXT_NAME"><![CDATA[名称]]></STRING>
	<STRING key="COLUMN_TEXT_FILE_NAME"><![CDATA[文件名]]></STRING>
	<STRING key="COLUMN_TEXT_COLOUR"><![CDATA[颜色]]></STRING>
	<STRING key="COLUMN_TEXT_CASTING_COST"><![CDATA[费用]]></STRING>
	<STRING key="COLUMN_TEXT_CASTING_COST_TEXT"><![CDATA[费用（文字）]]></STRING>
	<STRING key="COLUMN_TEXT_CMC"><![CDATA[费用值]]></STRING>
	<STRING key="COLUMN_TEXT_TYPE"><![CDATA[类别]]></STRING>
	<STRING key="COLUMN_TEXT_POWER"><![CDATA[力量]]></STRING>
	<STRING key="COLUMN_TEXT_TOUGHNESS"><![CDATA[防御力]]></STRING>
	<STRING key="COLUMN_TEXT_TOKEN"><![CDATA[衍生物]]></STRING>
	<STRING key="COLUMN_TEXT_WAD"><![CDATA[所在位置]]></STRING>
	<STRING key="COLUMN_TEXT_QUANTITY"><![CDATA[数量]]></STRING>
	<STRING key="COLUMN_TEXT_BIAS"><![CDATA[Bias]]></STRING>
	<STRING key="COLUMN_TEXT_PROMO"><![CDATA[闪卡]]></STRING>
	<STRING key="COLUMN_TEXT_UID"><![CDATA[ID]]></STRING>
	<STRING key="COLUMN_TEXT_CARD_COUNT"><![CDATA[Card Count]]></STRING>
	<STRING key="COLUMN_TEXT_BASIC_LANDS"><![CDATA[基本地]]></STRING>
	<STRING key="COLUMN_TEXT_REGULAR_UNLOCKS"><![CDATA[普通备牌]]></STRING>
	<STRING key="COLUMN_TEXT_PROMO_UNLOCKS"><![CDATA[额外闪卡备牌]]></STRING>
	<STRING key="COLUMN_TEXT_RARITY"><![CDATA[稀有度]]></STRING>
	<STRING key="COLUMN_TEXT_ARTIST"><![CDATA[画家]]></STRING>
	<STRING key="COLUMN_TEXT_EXPANSION"><![CDATA[版本]]></STRING>
	<!-- Strings for the Main Window -->
	<STRING key="DOUBLE_CLICK_MOVE"><![CDATA[双击以添加此牌到：]]></STRING>
	<STRING key="DECK"><![CDATA[套牌]]></STRING>
	<STRING key="BASIC_LAND"><![CDATA[基本地]]></STRING>
	<STRING key="EDIT_NAME"><![CDATA[编辑名称 ...]]></STRING>
	<STRING key="REGULAR_UNLOCKS"><![CDATA[普通备牌]]></STRING>
	<STRING key="PROMO_UNLOCKS"><![CDATA[额外闪卡备牌]]></STRING>
	<STRING key="CLEAR_FILTERS"><![CDATA[清除所有过滤选项]]></STRING>
	<STRING key="SET_FILTERS"><![CDATA[设置过滤选项 ...]]></STRING>
	<STRING key="SET_FILTERS_ADVANCED"><![CDATA[设置高级过滤选项 ...]]></STRING>
	<STRING key="DECK_OPEN_TITLE"><![CDATA[打开套牌 ...]]></STRING>
	<STRING key="DECK_SAVE_TITLE"><![CDATA[套牌另存为 ...]]></STRING>
	<STRING key="DECK_FILTER"><![CDATA[套牌文件 (*.xml)|*.xml|所有文件|*]]></STRING>
	<STRING key="CARD_SAVE_TITLE"><![CDATA[卡牌另存为 ...]]></STRING>
	<STRING key="CARD_FILTER"><![CDATA[卡牌代码文件 (*.xml)|*.xml|所有文件|*]]></STRING>
	<STRING key="UNABLE_TO_LOAD_DECK_CAPTION"><![CDATA[无法加载套牌。]]></STRING>
	<STRING key="UNABLE_TO_LOAD_DECK_MESSAGE"><![CDATA[无法加载选定套牌，请确认你选择文件的正确性和XML的有效性。]]></STRING>
	<STRING key="UNSAVED_WORK_CAPTION"><![CDATA[为保存的工作：现在保存吗？]]></STRING>
	<STRING key="UNSAVED_WORK_MESSAGE"><![CDATA[你有未保存的工作，你想现在保存这副套牌吗？]]></STRING>
	<STRING key="DECK_INFORMATION"><![CDATA[套牌信息 ...]]></STRING>
	<STRING key="EXPORT_COMPLETE_CAPTION"><![CDATA[导出成功。]]></STRING>
	<STRING key="EXPORT_COMPLETE_MESSAGE"><![CDATA[导出成功，此外已在你的WAD中生成一个自述文件。]]></STRING>
	<STRING key="EXPORT_UNSUCCESSFUL"><![CDATA[导出未完成，这可能是由于权限问题，但有关更多信息，请参阅错误日志。]]></STRING>
	<STRING key="UID_CONFLICT_DETECTED_CAPTION"><![CDATA[检测到的自定义ID的冲突！]]></STRING>
	<STRING key="UID_CONFLICT_DETECTED_MESSAGE"><![CDATA[为套牌生成自定义ID时检测到一个冲突，建议你不要进行下一步，请双击检查你的套牌信息。

你仍要继续吗？]]></STRING>
	<STRING key="SCHEME_ERROR_CAPTION"><![CDATA[无法继续。]]></STRING>
	<STRING key="SCHEME_ERROR_MESSAGE"><![CDATA[检查自定义ID的冲突时发生错误。这通常表明计划设置的ID或套牌本身的ID有问题。]]></STRING>
	<STRING key="COLUMNS"><![CDATA[&列]]></STRING>
	<STRING key="REMOVE_CARD"><![CDATA[&移除此牌]]></STRING>
	<STRING key="VIEW_CARD"><![CDATA[&查看牌文件 ...]]></STRING>
	<STRING key="DECKS_USED_IN"><![CDATA[&使用此牌的套牌 ...]]></STRING>
	<STRING key="DECKS_USING_CARD"><![CDATA[以下套牌使用了此牌：]]></STRING>
	<STRING key="NO_DECKS_USING_CARD"><![CDATA[此牌未被使用。]]></STRING>
	<STRING key="TOKEN_CREATED_BY_AND_USED_IN"><![CDATA[This card is created by {0} and used in decks:]]></STRING>
	<STRING key="TOKEN_CREATED_BY_AND_NOT_USED"><![CDATA[This card is created by {0}, but is not used.]]></STRING>
	<STRING key="IMAGE_SAVE_TITLE"><![CDATA[保存插图 ...]]></STRING>
	<STRING key="PNG_FILTER"><![CDATA[通常图像文件 (*.png)|*.png]]></STRING>
	<STRING key="TDX_FILTER"><![CDATA[游戏专用图像文件 (*.tdx)|*.tdx]]></STRING>
	<STRING key="CUSTOM_DATA_FOLDER_CREATED"><![CDATA[自定义数据目录 DATA_DLC_DECK_BUILDER_CUSTOM 已成功创建在游戏目录下。.]]></STRING>
	<STRING key="SAVE_CORE_WAD_AS"><![CDATA[核心WAD文件另存为 ...]]></STRING>
	<STRING key="WAD_FILTER"><![CDATA[游戏专用文件 (*.wad)|*.wad|所有文件|*]]></STRING>
	<STRING key="CREATE_CORE_WAD_SUCCESS"><![CDATA[成功由自定义数据创建核心WAD文件]]></STRING>
	<STRING key="LOADED_CARDS"><![CDATA[加载牌：]]></STRING>
	<STRING key="CARDS_IN_LIST"><![CDATA[牌所在列表：]]></STRING>
	<!-- Strings for use in generating a readme for the exported wad -->
	<!--	I don't really have any clue what I should put for a generic deck readme preamble so I just made some stuff up. -->
	<STRING key="README_PREAMBLE"><![CDATA[这套牌及其自述文件是由Riiak Shi Nal的2014套牌编辑器创建。
这个自述文件将使用当前语言列出套牌名称以及套牌的主牌表和备牌表，并列出所有依
赖的WAD文件（套牌中使用了那些文件中的牌）。

如果你希望成为一个modder（牌及套牌的制作者）或者对套牌编辑器有好的建议，请打
开以下网址（这是Collectible Card Games Headquarters论坛的旅法师对决板块）：
http://www.slightlymagic.net/forum/viewforum.php?f=62 ]]></STRING>
	<STRING key="README_DECK_NAME"><![CDATA[这套牌的名称：]]></STRING>
	<STRING key="README_CARDS_IN_DECK"><![CDATA[这套牌的主牌表：]]></STRING>
	<STRING key="README_CARDS_IN_REGULAR_UNLOCKS"><![CDATA[这套牌的普通备牌表：]]></STRING>
	<STRING key="README_CARDS_IN_PROMO_UNLOCKS"><![CDATA[这套牌的额外闪卡备牌表：]]></STRING>
	<STRING key="README_DEPENDS_ON_WADS"><![CDATA[这个WAD文件依赖的所有WAD文件（这个套牌中使用了那些文件中的牌）：]]></STRING>
	<!-- Strings for Deck Information Window -->
	<STRING key="BASIC_INFORMATION"><![CDATA[基本信息]]></STRING>
	<STRING key="DECK_AVAILABILITY"><![CDATA[套牌可用性：]]></STRING>
	<STRING key="LOCKED"><![CDATA[未解锁]]></STRING>
	<STRING key="NEVERAVAILABLE"><![CDATA[不可用]]></STRING>
	<STRING key="ALWAYSAVAILABLE"><![CDATA[可用]]></STRING>
	<STRING key="PREVIEW_CARD_SELECT"><![CDATA[用于预览的牌：]]></STRING>
	<STRING key="DECK_UID"><![CDATA[套牌标识：]]></STRING>
	<STRING key="FIRST_AVAILABLE_UID"><![CDATA[获取第一个可用的ID：]]></STRING>
	<STRING key="FINAL_UID"><![CDATA[最终确定的唯一ID：]]></STRING>
	<STRING key="DECK_STATISTICS"><![CDATA[套牌统计]]></STRING>
	<STRING key="CREATURE_SIZE"><![CDATA[生物大小：]]></STRING>
	<STRING key="SPEED"><![CDATA[套牌速度：]]></STRING>
	<STRING key="FLEXIBILITY"><![CDATA[套牌灵活度：]]></STRING>
	<STRING key="SYNERGY"><![CDATA[卡牌协同度：]]></STRING>
	<STRING key="LAND_CONFIG"><![CDATA[地牌调整]]></STRING>
	<STRING key="IGNORE_CMC_OVER"><![CDATA[忽略套牌颜色对基本地分配的影响：]]></STRING>
	<STRING key="MIN_FORESTS"><![CDATA[树林最少用量：]]></STRING>
	<STRING key="MIN_ISLANDS"><![CDATA[海岛最少用量：]]></STRING>
	<STRING key="MIN_MOUNTAINS"><![CDATA[山脉最少用量：]]></STRING>
	<STRING key="MIN_PLAINS"><![CDATA[平原最少用量：]]></STRING>
	<STRING key="MIN_SWAMPS"><![CDATA[沼泽最少用量：]]></STRING>
	<STRING key="NUM_SPELLS_THAT_COUNT_AS_LAND"><![CDATA[牌表中地牌的数量]]></STRING>
	<STRING key="PROBLEM_WITH_SCHEME_SETTINGS_CAPTION"><![CDATA[ID方案的问题。]]></STRING>
	<STRING key="PROBLEM_WITH_SCHEME_SETTINGS_MESSAGE"><![CDATA[我们在为此套牌寻找一个未被使用的ID是遇到问题，请检查你的ID方案。]]></STRING>
	<STRING key="NO_AVAILABLE_IDS_CAPTION"><![CDATA[没有可用ID！]]></STRING>
	<STRING key="NO_AVAILABLE_IDS_MESSAGE"><![CDATA[我们无法根据当前的ID方案找到一个可用的ID。]]></STRING>
	<STRING key="DECK_BOX"><![CDATA[牌盒]]></STRING>
	<STRING key="USE_DECK_IMAGE"><![CDATA[使用套牌图像]]></STRING>
	<STRING key="USE_THIS_IMAGE"><![CDATA[使用这个图像]]></STRING>
	<STRING key="LOAD_IMAGE"><![CDATA[加载一个图片]]></STRING>
	<STRING key="LOAD_IMAGE_CAPTION"><![CDATA[加载图片 ...]]></STRING>
	<STRING key="EDIT_PERSONALITY"><![CDATA[编辑个人头像 ...]]></STRING>
	<!-- Technically .Net also supports EXIF & TIFF, but I don't see those being commonly used so I omitted them from the filter. -->
	<STRING key="LOAD_IMAGE_FILTER"><![CDATA[支持的图片类别 (*.bmp, *.gif, *.jpg, *.jpeg, *.png, *.tdx)|*.bmp;*.gif;*.jpg;*.jpeg;*.png;*.tdx|Bitmap (*.bmp)|*.bmp|Compuserve Image (*.gif)|*.gif|Joint Photographic Experts Group Image (*.jpg, *.jpeg)|*.jpg;*.jpeg|Portable Network Graphics (*.png)|*.png|DotP Image Format (*.tdx)|*.tdx|All Files|*]]></STRING>
	<STRING key="BUILD_IMAGE"><![CDATA[创建一个牌盒图片]]></STRING>
	<STRING key="LOCATION"><![CDATA[位置]]></STRING>
	<STRING key="SIZE"><![CDATA[尺寸]]></STRING>
	<STRING key="AI_PERSONALITY"><![CDATA[AI的头像]]></STRING>
	<STRING key="MUSIC"><![CDATA[音乐：]]></STRING>
	<!-- Strings for the Create From Existing Deck window -->
	<STRING key="CHOOSE_DECK"><![CDATA[选择一个现有套牌 ...]]></STRING>
	<!-- Strings for the Id Schemes -->
	<STRING key="ADDITIVESCHEME"><![CDATA[完整模式（设置的ID将作为最终ID。）]]></STRING>
	<STRING key="PREFIXSCHEME"><![CDATA[前缀模式（设置的ID将作为最终ID的前缀。）]]></STRING>
	<STRING key="SUFFIXSCHEME"><![CDATA[后缀模式（设置的ID将作为最终ID的后缀。）]]></STRING>
	<!-- Strings for Refresh Data Warning -->
	<STRING key="REFRESH_DATA_WARNING_TEXT"><![CDATA[刷新数据将导致所有未保存的数据和更改丢失。
你还要继续吗？]]></STRING>
	<STRING key="REFRESH_DATA_WARNING_CAPTION"><![CDATA[警告：未保存的数据将丢失！]]></STRING>
	<!-- Strings for Options window -->
	<STRING key="FORM_CAPTION_OPTIONS"><![CDATA[选项]]></STRING>
	<STRING key="APPLY"><![CDATA[&确定]]></STRING>
	<STRING key="CANCEL"><![CDATA[&取消]]></STRING>
	<STRING key="BROWSE"><![CDATA[浏览 ...]]></STRING>
	<STRING key="GENERAL_OPTIONS"><![CDATA[常规选项]]></STRING>
	<STRING key="DOTP_2014_DIRECTORY"><![CDATA[万智牌2014根目录]]></STRING>
	<STRING key="LANGAUGE"><![CDATA[语言]]></STRING>
	<STRING key="PERFORM_BASIC_SCREEN_CHECKS"><![CDATA[Perform basic screen checks when restoring windows]]></STRING>
	<STRING key="NEED_VALID_GAME_DRIECTORY_CAPTION"><![CDATA[需要有效的游戏根目录]]></STRING>
	<STRING key="NEED_VALID_GAME_DRIECTORY_MESSAGE"><![CDATA[不设置万智牌2014游戏目录将无法继续。
请先选择游戏根目录。]]></STRING>
	<STRING key="CHOOSE_DIRECTORY_FILTER"><![CDATA[游戏执行文件 (DotP_D14.exe)|DotP_D14.exe|所有文件|*]]></STRING>
	<STRING key="CHOOSE_DIRECTORY_TITLE"><![CDATA[选择万智牌2014根目录]]></STRING>
	<STRING key="ID_SCHEME"><![CDATA[ID编号方案]]></STRING>
	<STRING key="SCHEME_TYPE"><![CDATA[方案种类：]]></STRING>
	<STRING key="SCHEME_ID_MINIMUM_DIGITS"><![CDATA[ID最小位数：]]></STRING>
	<STRING key="MINIMUM_ID"><![CDATA[可接受的最小ID：]]></STRING>
	<STRING key="MAXIMUM_ID"><![CDATA[可接受的最大ID：]]></STRING>
	<STRING key="USE_ID_BLOCK"><![CDATA[使用统一的ID：]]></STRING>
	<STRING key="DECK_ID_CHANGE"><![CDATA[设置套牌ID：]]></STRING>
	<STRING key="LAND_POOL_ID_CHANGE"><![CDATA[设置地牌牌池ID：]]></STRING>
	<STRING key="REGULAR_UNLOCK_ID_CHANGE"><![CDATA[设置普通备牌ID：]]></STRING>
	<STRING key="PROMO_UNLOCK_ID_CHANGE"><![CDATA[设置额外闪卡备牌ID：]]></STRING>
	<STRING key="ID_SCHEME_EXAMPLE"><![CDATA[ID方案示例：]]></STRING>
	<STRING key="INVALID"><![CDATA[(Invalid)]]></STRING>
	<STRING key="PRE_SHUFFLE_ON_EXPORT"><![CDATA[Pre-Shuffle Deck on Export]]></STRING>
	<STRING key="INCLUDE_MIPMAPS_TDX"><![CDATA[在TDX文件（游戏图片文件的格式，比如牌的插画等）中包含MipMaps（不懂请百度）。]]></STRING>
	<!-- Strings for Filter Settings window -->
	<STRING key="FILTER_SETTINGS"><![CDATA[过滤器设置 ...]]></STRING>
	<STRING key="CARD_NAME"><![CDATA[卡牌名称]]></STRING>
	<STRING key="CHECK_CARD_NAME"><![CDATA[检查卡牌名称]]></STRING>
	<STRING key="CONTAINS"><![CDATA[包含]]></STRING>
	<STRING key="DOESNOTCONTAIN"><![CDATA[不包含]]></STRING>
	<STRING key="EQUAL"><![CDATA[相同]]></STRING>
	<STRING key="NOTEQUAL"><![CDATA[不相同]]></STRING>
	<STRING key="GREATERTHAN"><![CDATA[大于]]></STRING>
	<STRING key="GREATERTHANOREQUALTO"><![CDATA[大于等于]]></STRING>
	<STRING key="LESSTHAN"><![CDATA[小于]]></STRING>
	<STRING key="LESSTHANOREQUALTO"><![CDATA[小于等于]]></STRING>
	<STRING key="ALLOW"><![CDATA[包含已勾选项]]></STRING>
	<STRING key="ALLOWANY"><![CDATA[只包含已勾选项]]></STRING>
	<STRING key="EXACTMATCH"><![CDATA[等于已勾选项]]></STRING>
	<STRING key="EXCLUDE"><![CDATA[不包含已勾选项]]></STRING>
	<STRING key="COLOUR"><![CDATA[颜色]]></STRING>
	<STRING key="TYPES"><![CDATA[类别]]></STRING>
	<STRING key="SUPERTYPE"><![CDATA[超类别]]></STRING>
	<STRING key="SUB_TYPES"><![CDATA[副类别]]></STRING>
	<STRING key="CHECK_SUB_TYPE"><![CDATA[检查副类别]]></STRING>
	<STRING key="CONVERTED_MANA_COST"><![CDATA[法术力费用]]></STRING>
	<STRING key="POWER_TOUGHNESS"><![CDATA[力量 && 防御力]]></STRING>
	<STRING key="CHECK_POWER_TOUGHNESS"><![CDATA[检查 力量/防御力]]></STRING>
	<STRING key="RARITY"><![CDATA[稀有度]]></STRING>
	<STRING key="RARITY_TOKEN"><![CDATA[衍生物]]></STRING>
	<STRING key="RARITY_LAND"><![CDATA[地]]></STRING>
	<STRING key="RARITY_COMMON"><![CDATA[普通]]></STRING>
	<STRING key="RARITY_UNCOMMON"><![CDATA[非普通]]></STRING>
	<STRING key="RARITY_RARE"><![CDATA[稀有]]></STRING>
	<STRING key="RARITY_MYTHIC"><![CDATA[秘稀]]></STRING>
	<STRING key="ABILITIES"><![CDATA[异能]]></STRING>
	<STRING key="CHECK_ABILITIES"><![CDATA[检查异能]]></STRING>
	<STRING key="CHECK_GRANTED_ABILITIES"><![CDATA[检查赋予其它牌的异能]]></STRING>
	<STRING key="EXTRA_FILTERS"><![CDATA[额外的过滤选项]]></STRING>
	<STRING key="TOKENS"><![CDATA[是否衍生物]]></STRING>
	<STRING key="CARDS_THAT_CREATE_TOKENS"><![CDATA[产生衍生物的牌]]></STRING>
	<STRING key="USES_REGULAR_MANA"><![CDATA[只具有普通法术力]]></STRING>
	<STRING key="USES_HYBRID_MANA"><![CDATA[具有混色法术力]]></STRING>
	<STRING key="USES_PHYREXIAN_MANA"><![CDATA[具有非瑞克西亚法术力]]></STRING>
	<!-- String for the Advanced Card Filters -->
	<STRING key="BOOLIS"><![CDATA[Card is/has/can]]></STRING>
	<STRING key="BOOLISNOT"><![CDATA[Card is not/does not have/can't]]></STRING>
	<STRING key="ENUMIS"><![CDATA[Is]]></STRING>
	<STRING key="ENUMISNOT"><![CDATA[Is Not]]></STRING>
	<STRING key="CARD_FILTER_ADVANCED_SETTINGS"><![CDATA[Advanced Card Filter Settings]]></STRING>
	<STRING key="CARD_FILTER_SET"><![CDATA[Filter Set]]></STRING>
	<STRING key="CARD_FILTER_BOOLEAN"><![CDATA[Boolean Filters]]></STRING>
	<STRING key="CARD_FILTER_INTEGER"><![CDATA[Integer Filters]]></STRING>
	<STRING key="CARD_FILTER_STRING"><![CDATA[String Filters]]></STRING>
	<STRING key="CARD_FILTER_ENUM"><![CDATA[Enum Filters]]></STRING>
	<STRING key="CARD_FILTER_POWER_TOUGHNESS"><![CDATA[Power/Toughness]]></STRING>
	<STRING key="CARD_FILTER_CLEAR"><![CDATA[Clear Filters]]></STRING>
	<STRING key="CARD_FILTER_ADD"><![CDATA[Add Filter]]></STRING>
	<STRING key="CARD_FILTER_ADD_SET"><![CDATA[Add Filter Set]]></STRING>
	<STRING key="CARD_FILTER_REPLACE"><![CDATA[Replace Selected Filter]]></STRING>
	<STRING key="CARD_FILTER_COMPARE_WITH_NEXT_FILTER"><![CDATA[Comparison with Next Filter:]]></STRING>
	<STRING key="CARD_FILTER_SET_NEGATE"><![CDATA[Negate the Filter Results of the Set]]></STRING>
	<STRING key="CARD_FILTER_COMPARE_AND"><![CDATA[And]]></STRING>
	<STRING key="CARD_FILTER_COMPARE_OR"><![CDATA[Or]]></STRING>
	<!-- For these strings {0} is localized "And" or "Or". -->
	<STRING key="CARD_FILTER_SET_COMPARE"><![CDATA[Result from Set {0}]]></STRING>
	<STRING key="CARD_FILTER_SET_NOT_COMPARE"><![CDATA[Not Result from Set {0}]]></STRING>
	<!-- These strings are used to build equations for Integer filters
		in the form: "Converted Mana Cost <= 4 And"
		I chose to do it this way because math equations are pretty well
		recognized in all languages in this form. -->
	<STRING key="CARD_FILTER_INT_COMPARISON_EQUAL"><![CDATA[==]]></STRING>
	<STRING key="CARD_FILTER_INT_COMPARISON_GREATERTHAN"><![CDATA[>]]></STRING>
	<STRING key="CARD_FILTER_INT_COMPARISON_GREATERTHANOREQUALTO"><![CDATA[>=]]></STRING>
	<STRING key="CARD_FILTER_INT_COMPARISON_LESSTHAN"><![CDATA[<]]></STRING>
	<STRING key="CARD_FILTER_INT_COMPARISON_LESSTHANOREQUALTO"><![CDATA[<=]]></STRING>
	<STRING key="CARD_FILTER_INT_COMPARISON_NOTEQUAL"><![CDATA[!=]]></STRING>
	<!-- For these strings {0} is the localized data property name,
		{1} is the value the user entered, and {2} is localized "And" or "Or".
		For Example: "{0} contains {1} {2}" => "Ability constains Destroy And"
					"{0} is {1} {2}" => "Card Type is Artifact Or" -->
	<STRING key="CARD_FILTER_STRING_COMPARISON_CONTAINS"><![CDATA[{0} contains {1} {2}]]></STRING>
	<STRING key="CARD_FILTER_STRING_COMPARISON_DOESNOTCONTAIN"><![CDATA[{0} does not contain {1} {2}]]></STRING>
	<STRING key="CARD_FILTER_STRING_COMPARISON_EQUAL"><![CDATA[{0} equals {1} {2}]]></STRING>
	<STRING key="CARD_FILTER_STRING_COMPARISON_NOTEQUAL"><![CDATA[{0} is not equal to {1} {2}]]></STRING>
	<STRING key="CARD_FILTER_ENUM_COMPARISON_ENUMIS"><![CDATA[{0} is {1} {2}]]></STRING>
	<STRING key="CARD_FILTER_ENUM_COMPARISON_ENUMISNOT"><![CDATA[{0} is not {1} {2}]]></STRING>
	<!-- For these strings {0} is the localized data property name and
		{1} is the localized "And" or "Or".
		For Example: "Card is/has/can {0} {1}" => "Card is/has/can Token And"
					"Card is/has/can {0} {1}" => "Card is/has/can Phyrexian Mana Or" -->
	<STRING key="CARD_FILTER_BOOL_COMPARISON_BOOLIS"><![CDATA[Card is/has/can {0} {1}]]></STRING>
	<STRING key="CARD_FILTER_BOOL_COMPARISON_BOOLISNOT"><![CDATA[Card is not/does not have/can't {0} {1}]]></STRING>
	<STRING key="CARD_FILTER_PROP_ARTIST"><![CDATA[Artist]]></STRING>
	<STRING key="CARD_FILTER_PROP_CARDXML"><![CDATA[Card XML]]></STRING>
	<STRING key="CARD_FILTER_PROP_CASTINGCOST"><![CDATA[Casting Cost]]></STRING>
	<STRING key="CARD_FILTER_PROP_COLOUR"><![CDATA[Colour]]></STRING>
	<STRING key="CARD_FILTER_PROP_CONVERTEDMANACOST"><![CDATA[Converted Mana Cost]]></STRING>
	<STRING key="CARD_FILTER_PROP_CREATETOKENS"><![CDATA[Create Tokens]]></STRING>
	<STRING key="CARD_FILTER_PROP_EXPANSION"><![CDATA[Expansion]]></STRING>
	<STRING key="CARD_FILTER_PROP_FILENAME"><![CDATA[Filename]]></STRING>
	<STRING key="CARD_FILTER_PROP_HYBRIDMANA"><![CDATA[Hybrid Mana]]></STRING>
	<STRING key="CARD_FILTER_PROP_IMAGEFILENAME"><![CDATA[Image Filename]]></STRING>
	<STRING key="CARD_FILTER_PROP_LOCALIZEDABILITIESTEXT"><![CDATA[Abilities]]></STRING>
	<STRING key="CARD_FILTER_PROP_LOCALIZEDFLAVOUR"><![CDATA[Flavour]]></STRING>
	<STRING key="CARD_FILTER_PROP_LOCALIZEDNAME"><![CDATA[Name]]></STRING>
	<STRING key="CARD_FILTER_PROP_MULTIVERSEID"><![CDATA[Multiverse Id]]></STRING>
	<STRING key="CARD_FILTER_PROP_PHYREXIANMANA"><![CDATA[Phyrexian Mana]]></STRING>
	<STRING key="CARD_FILTER_PROP_POWER"><![CDATA[Power]]></STRING>
	<STRING key="CARD_FILTER_PROP_PRESENTINWAD"><![CDATA[Wad]]></STRING>
	<STRING key="CARD_FILTER_PROP_RARITY"><![CDATA[Rarity]]></STRING>
	<STRING key="CARD_FILTER_PROP_REGISTEREDTOKENSTEXT"><![CDATA[Tokens Created]]></STRING>
	<STRING key="CARD_FILTER_PROP_SUBTYPES"><![CDATA[Sub-Type]]></STRING>
	<STRING key="CARD_FILTER_PROP_SUPERTYPES"><![CDATA[Supertype]]></STRING>
	<STRING key="CARD_FILTER_PROP_TOUGHNESS"><![CDATA[Toughness]]></STRING>
	<STRING key="CARD_FILTER_PROP_TYPE"><![CDATA[Type]]></STRING>
	<STRING key="CARD_FILTER_PROP_TOKEN"><![CDATA[Token]]></STRING>
	<!-- Strings for the Colours -->
	<STRING key="MANA_BLACK"><![CDATA[黑色]]></STRING>
	<STRING key="MANA_BLUE"><![CDATA[蓝色]]></STRING>
	<STRING key="MANA_COLOURLESS"><![CDATA[无色]]></STRING>
	<STRING key="MANA_GREEN"><![CDATA[绿色]]></STRING>
	<STRING key="MANA_RED"><![CDATA[红色]]></STRING>
	<STRING key="MANA_WHITE"><![CDATA[白色]]></STRING>
	<STRING key="MANA_MULTICOLOUR"><![CDATA[多色]]></STRING>
	<STRING key="MANA_NOTDEFINED"><![CDATA[不定义颜色]]></STRING>
	<!-- Strings for the Card Supertypes -->
	<STRING key="CARD_SUPERTYPE_BASIC"><![CDATA[基本]]></STRING>
	<STRING key="CARD_SUPERTYPE_LEGENDARY"><![CDATA[传奇]]></STRING>
	<STRING key="CARD_SUPERTYPE_ONGOING"><![CDATA[Ongoing]]></STRING>
	<STRING key="CARD_SUPERTYPE_SNOW"><![CDATA[雪境]]></STRING>
	<STRING key="CARD_SUPERTYPE_WORLD"><![CDATA[世界]]></STRING>
	<!-- Strings for the Card Types -->
	<STRING key="CARD_TYPE_ARTIFACT"><![CDATA[神器]]></STRING>
	<STRING key="CARD_TYPE_CREATURE"><![CDATA[生物]]></STRING>
	<STRING key="CARD_TYPE_ENCHANTMENT"><![CDATA[结界]]></STRING>
	<STRING key="CARD_TYPE_INSTANT"><![CDATA[瞬间]]></STRING>
	<STRING key="CARD_TYPE_LAND"><![CDATA[地]]></STRING>
	<STRING key="CARD_TYPE_PHENOMENON"><![CDATA[奇迹]]></STRING>
	<STRING key="CARD_TYPE_PLANE"><![CDATA[地域]]></STRING>
	<STRING key="CARD_TYPE_PLANESWALKER"><![CDATA[鹏洛克]]></STRING>
	<STRING key="CARD_TYPE_SCHEME"><![CDATA[暴政]]></STRING>
	<STRING key="CARD_TYPE_SORCERY"><![CDATA[法术]]></STRING>
	<STRING key="CARD_TYPE_TRIBAL"><![CDATA[部族]]></STRING>
	<STRING key="CARD_TYPE_VANGUARD"><![CDATA[先锋]]></STRING>
	<!-- Strings for the Card Sub-Types - Artifact -->
	<STRING key="CARD_SUBTYPE_CONTRAPTION"><![CDATA[装置]]></STRING>
	<STRING key="CARD_SUBTYPE_EQUIPMENT"><![CDATA[武具]]></STRING>
	<STRING key="CARD_SUBTYPE_FORTIFICATION"><![CDATA[工事]]></STRING>
	<!-- Strings for the Card Sub-Types - Creature -->
	<STRING key="CARD_SUBTYPE_ADVISOR"><![CDATA[参谋]]></STRING>
	<STRING key="CARD_SUBTYPE_ALLIGATOR"><![CDATA[鳄鱼（无）]]></STRING>
	<STRING key="CARD_SUBTYPE_ALLY"><![CDATA[伙伴]]></STRING>
	<STRING key="CARD_SUBTYPE_ANEMONE"><![CDATA[海葵]]></STRING>
	<STRING key="CARD_SUBTYPE_ANGEL"><![CDATA[天使]]></STRING>
	<STRING key="CARD_SUBTYPE_ANTEATER"><![CDATA[食蚁兽]]></STRING>
	<STRING key="CARD_SUBTYPE_ANTELOPE"><![CDATA[羚羊]]></STRING>
	<STRING key="CARD_SUBTYPE_APE"><![CDATA[猿猴]]></STRING>
	<STRING key="CARD_SUBTYPE_ARCHER"><![CDATA[弓箭手]]></STRING>
	<STRING key="CARD_SUBTYPE_ARCHON"><![CDATA[统领]]></STRING>
	<STRING key="CARD_SUBTYPE_ARTIFICER"><![CDATA[神器师]]></STRING>
	<STRING key="CARD_SUBTYPE_ASSASSIN"><![CDATA[杀手]]></STRING>
	<STRING key="CARD_SUBTYPE_ASSEMBLY_WORKER"><![CDATA[组装工人]]></STRING>
	<STRING key="CARD_SUBTYPE_ATOG"><![CDATA[阿托格]]></STRING>
	<STRING key="CARD_SUBTYPE_AUROCHS"><![CDATA[原牛]]></STRING>
	<STRING key="CARD_SUBTYPE_AVATAR"><![CDATA[圣者]]></STRING>
	<STRING key="CARD_SUBTYPE_BADGER"><![CDATA[獾]]></STRING>
	<STRING key="CARD_SUBTYPE_BARBARIAN"><![CDATA[野蛮人]]></STRING>
	<STRING key="CARD_SUBTYPE_BASILISK"><![CDATA[蜥怪]]></STRING>
	<STRING key="CARD_SUBTYPE_BAT"><![CDATA[蝙蝠]]></STRING>
	<STRING key="CARD_SUBTYPE_BEAR"><![CDATA[熊]]></STRING>
	<STRING key="CARD_SUBTYPE_BEAST"><![CDATA[野兽]]></STRING>
	<STRING key="CARD_SUBTYPE_BEEBLE"><![CDATA[哔宝精]]></STRING>
	<STRING key="CARD_SUBTYPE_BERSERKER"><![CDATA[狂战士]]></STRING>
	<STRING key="CARD_SUBTYPE_BIRD"><![CDATA[鸟]]></STRING>
	<STRING key="CARD_SUBTYPE_BLINKMOTH"><![CDATA[光蛾]]></STRING>
	<STRING key="CARD_SUBTYPE_BOAR"><![CDATA[野猪]]></STRING>
	<STRING key="CARD_SUBTYPE_BRINGER"><![CDATA[信使]]></STRING>
	<STRING key="CARD_SUBTYPE_BRUSHWAGG"><![CDATA[丛枝兽]]></STRING>
	<STRING key="CARD_SUBTYPE_CAMARID"><![CDATA[卡马利]]></STRING>
	<STRING key="CARD_SUBTYPE_CAMEL"><![CDATA[骆驼]]></STRING>
	<STRING key="CARD_SUBTYPE_CARIBOU"><![CDATA[驯鹿]]></STRING>
	<STRING key="CARD_SUBTYPE_CARRIER"><![CDATA[病媒]]></STRING>
	<STRING key="CARD_SUBTYPE_CAT"><![CDATA[猫]]></STRING>
	<STRING key="CARD_SUBTYPE_CENTAUR"><![CDATA[半人马]]></STRING>
	<STRING key="CARD_SUBTYPE_CEPHALID"><![CDATA[章人]]></STRING>
	<STRING key="CARD_SUBTYPE_CHIMERA"><![CDATA[盖美拉]]></STRING>
	<STRING key="CARD_SUBTYPE_CITIZEN"><![CDATA[市民]]></STRING>
	<STRING key="CARD_SUBTYPE_CLERIC"><![CDATA[僧侣]]></STRING>
	<STRING key="CARD_SUBTYPE_COCKATRICE"><![CDATA[石化鸡蛇]]></STRING>
	<STRING key="CARD_SUBTYPE_COLOSSUS"><![CDATA[巨像（无）]]></STRING>
	<STRING key="CARD_SUBTYPE_CONSTRUCT"><![CDATA[组构体]]></STRING>
	<STRING key="CARD_SUBTYPE_COWARD"><![CDATA[懦夫]]></STRING>
	<STRING key="CARD_SUBTYPE_CRAB"><![CDATA[蟹]]></STRING>
	<STRING key="CARD_SUBTYPE_CROCODILE"><![CDATA[鳄鱼]]></STRING>
	<STRING key="CARD_SUBTYPE_CYCLOPS"><![CDATA[独眼巨人]]></STRING>
	<STRING key="CARD_SUBTYPE_DAUTHI"><![CDATA[道西]]></STRING>
	<STRING key="CARD_SUBTYPE_DEMON"><![CDATA[恶魔]]></STRING>
	<STRING key="CARD_SUBTYPE_DESERTER"><![CDATA[逃兵]]></STRING>
	<STRING key="CARD_SUBTYPE_DEVIL"><![CDATA[魔鬼]]></STRING>
	<STRING key="CARD_SUBTYPE_DJINN"><![CDATA[巨灵]]></STRING>
	<STRING key="CARD_SUBTYPE_DRAGON"><![CDATA[龙]]></STRING>
	<STRING key="CARD_SUBTYPE_DRAKE"><![CDATA[龙兽]]></STRING>
	<STRING key="CARD_SUBTYPE_DREADNOUGHT"><![CDATA[无畏舰]]></STRING>
	<STRING key="CARD_SUBTYPE_DRONE"><![CDATA[奴兽]]></STRING>
	<STRING key="CARD_SUBTYPE_DRUID"><![CDATA[德鲁伊]]></STRING>
	<STRING key="CARD_SUBTYPE_DRYAD"><![CDATA[树灵]]></STRING>
	<STRING key="CARD_SUBTYPE_DWARF"><![CDATA[矮人]]></STRING>
	<STRING key="CARD_SUBTYPE_EFREET"><![CDATA[魔神]]></STRING>
	<STRING key="CARD_SUBTYPE_EGG"><![CDATA[蛋]]></STRING>
	<STRING key="CARD_SUBTYPE_ELDER"><![CDATA[长老]]></STRING>
	<STRING key="CARD_SUBTYPE_ELDRAZI"><![CDATA[奥札奇]]></STRING>
	<STRING key="CARD_SUBTYPE_ELEMENTAL"><![CDATA[元素]]></STRING>
	<STRING key="CARD_SUBTYPE_ELEPHANT"><![CDATA[象]]></STRING>
	<STRING key="CARD_SUBTYPE_ELF"><![CDATA[妖精]]></STRING>
	<STRING key="CARD_SUBTYPE_ELK"><![CDATA[麋鹿]]></STRING>
	<STRING key="CARD_SUBTYPE_EYE"><![CDATA[眼]]></STRING>
	<STRING key="CARD_SUBTYPE_FAERIE"><![CDATA[仙灵]]></STRING>
	<STRING key="CARD_SUBTYPE_FERRET"><![CDATA[雪貂]]></STRING>
	<STRING key="CARD_SUBTYPE_FISH"><![CDATA[鱼]]></STRING>
	<STRING key="CARD_SUBTYPE_FLAGBEARER"><![CDATA[旗手]]></STRING>
	<STRING key="CARD_SUBTYPE_FOX"><![CDATA[狐]]></STRING>
	<STRING key="CARD_SUBTYPE_FROG"><![CDATA[蛙]]></STRING>
	<STRING key="CARD_SUBTYPE_FUNGUS"><![CDATA[真菌]]></STRING>
	<STRING key="CARD_SUBTYPE_GARGOYLE"><![CDATA[石像鬼]]></STRING>
	<STRING key="CARD_SUBTYPE_GENERAL"><![CDATA[将军（无）]]></STRING>
	<STRING key="CARD_SUBTYPE_GERM"><![CDATA[病菌]]></STRING>
	<STRING key="CARD_SUBTYPE_GIANT"><![CDATA[巨人]]></STRING>
	<STRING key="CARD_SUBTYPE_GNOME"><![CDATA[地侏]]></STRING>
	<STRING key="CARD_SUBTYPE_GOAT"><![CDATA[山羊]]></STRING>
	<STRING key="CARD_SUBTYPE_GOBLIN"><![CDATA[鬼怪]]></STRING>
	<STRING key="CARD_SUBTYPE_GOLEM"><![CDATA[魔像]]></STRING>
	<STRING key="CARD_SUBTYPE_GORGON"><![CDATA[蛇发妖]]></STRING>
	<STRING key="CARD_SUBTYPE_GRAVEBORN"><![CDATA[墓生]]></STRING>
	<STRING key="CARD_SUBTYPE_GREMLIN"><![CDATA[怪灵]]></STRING>
	<STRING key="CARD_SUBTYPE_GRIFFIN"><![CDATA[狮鹫]]></STRING>
	<STRING key="CARD_SUBTYPE_HAG"><![CDATA[巫婆]]></STRING>
	<STRING key="CARD_SUBTYPE_HARPY"><![CDATA[哈痞]]></STRING>
	<STRING key="CARD_SUBTYPE_HELLION"><![CDATA[地狱兽]]></STRING>
	<STRING key="CARD_SUBTYPE_HIPPO"><![CDATA[河马]]></STRING>
	<STRING key="CARD_SUBTYPE_HIPPOGRIFF"><![CDATA[骏鹰]]></STRING>
	<STRING key="CARD_SUBTYPE_HOMARID"><![CDATA[荷马利]]></STRING>
	<STRING key="CARD_SUBTYPE_HOMUNCULUS"><![CDATA[造妖]]></STRING>
	<STRING key="CARD_SUBTYPE_HORROR"><![CDATA[惊惧兽]]></STRING>
	<STRING key="CARD_SUBTYPE_HORSE"><![CDATA[马]]></STRING>
	<STRING key="CARD_SUBTYPE_HOUND"><![CDATA[猎犬]]></STRING>
	<STRING key="CARD_SUBTYPE_HUMAN"><![CDATA[人类]]></STRING>
	<STRING key="CARD_SUBTYPE_HYDRA"><![CDATA[多头龙]]></STRING>
	<STRING key="CARD_SUBTYPE_HYENA"><![CDATA[鬣狗]]></STRING>
	<STRING key="CARD_SUBTYPE_ILLUSION"><![CDATA[虚影]]></STRING>
	<STRING key="CARD_SUBTYPE_IMP"><![CDATA[小恶魔]]></STRING>
	<STRING key="CARD_SUBTYPE_INCARNATION"><![CDATA[化身]]></STRING>
	<STRING key="CARD_SUBTYPE_INSECT"><![CDATA[昆虫]]></STRING>
	<STRING key="CARD_SUBTYPE_JELLYFISH"><![CDATA[水母]]></STRING>
	<STRING key="CARD_SUBTYPE_JUGGERNAUT"><![CDATA[攻城巨车]]></STRING>
	<STRING key="CARD_SUBTYPE_KAVU"><![CDATA[卡甫]]></STRING>
	<STRING key="CARD_SUBTYPE_KIRIN"><![CDATA[麒麟]]></STRING>
	<STRING key="CARD_SUBTYPE_KITHKIN"><![CDATA[洁瑛]]></STRING>
	<STRING key="CARD_SUBTYPE_KNIGHT"><![CDATA[骑士]]></STRING>
	<STRING key="CARD_SUBTYPE_KOBOLD"><![CDATA[鬼崽]]></STRING>
	<STRING key="CARD_SUBTYPE_KOR"><![CDATA[寇族]]></STRING>
	<STRING key="CARD_SUBTYPE_KRAKEN"><![CDATA[巨海兽]]></STRING>
	<STRING key="CARD_SUBTYPE_LAMMASU"><![CDATA[拉玛苏]]></STRING>
	<STRING key="CARD_SUBTYPE_LEECH"><![CDATA[蛭]]></STRING>
	<STRING key="CARD_SUBTYPE_LEVIATHAN"><![CDATA[海怪]]></STRING>
	<STRING key="CARD_SUBTYPE_LHURGOYF"><![CDATA[拉高耶夫]]></STRING>
	<STRING key="CARD_SUBTYPE_LICID"><![CDATA[立吸怪]]></STRING>
	<STRING key="CARD_SUBTYPE_LIZARD"><![CDATA[蜥蜴]]></STRING>
	<STRING key="CARD_SUBTYPE_MANTICORE"><![CDATA[翼狮]]></STRING>
	<STRING key="CARD_SUBTYPE_MASTICORE"><![CDATA[异狮]]></STRING>
	<STRING key="CARD_SUBTYPE_MERCENARY"><![CDATA[佣兵]]></STRING>
	<STRING key="CARD_SUBTYPE_MERFOLK"><![CDATA[人鱼]]></STRING>
	<STRING key="CARD_SUBTYPE_METATHRAN"><![CDATA[仿索蓝人]]></STRING>
	<STRING key="CARD_SUBTYPE_MINION"><![CDATA[奴仆]]></STRING>
	<STRING key="CARD_SUBTYPE_MINOTAUR"><![CDATA[牛头怪]]></STRING>
	<STRING key="CARD_SUBTYPE_MONGER"><![CDATA[贩商]]></STRING>
	<STRING key="CARD_SUBTYPE_MONGOOSE"><![CDATA[猫鼬]]></STRING>
	<STRING key="CARD_SUBTYPE_MONK"><![CDATA[修行僧]]></STRING>
	<STRING key="CARD_SUBTYPE_MOONFOLK"><![CDATA[月人]]></STRING>
	<STRING key="CARD_SUBTYPE_MUTANT"><![CDATA[突变体]]></STRING>
	<STRING key="CARD_SUBTYPE_MYR"><![CDATA[秘耳]]></STRING>
	<STRING key="CARD_SUBTYPE_MYSTIC"><![CDATA[秘教徒]]></STRING>
	<STRING key="CARD_SUBTYPE_NAUTILUS"><![CDATA[鹦鹂螺]]></STRING>
	<STRING key="CARD_SUBTYPE_NEPHILIM"><![CDATA[巨神灵]]></STRING>
	<STRING key="CARD_SUBTYPE_NEWT"><![CDATA[水蠑（无）]]></STRING>
	<STRING key="CARD_SUBTYPE_NIGHTMARE"><![CDATA[梦魇]]></STRING>
	<STRING key="CARD_SUBTYPE_NIGHTSTALKER"><![CDATA[夜潜魔]]></STRING>
	<STRING key="CARD_SUBTYPE_NINJA"><![CDATA[忍者]]></STRING>
	<STRING key="CARD_SUBTYPE_NOBLE"><![CDATA[贵族（无）]]></STRING>
	<STRING key="CARD_SUBTYPE_NOGGLE"><![CDATA[诺格]]></STRING>
	<STRING key="CARD_SUBTYPE_NOMAD"><![CDATA[游牧人]]></STRING>
	<STRING key="CARD_SUBTYPE_OCTOPUS"><![CDATA[章鱼]]></STRING>
	<STRING key="CARD_SUBTYPE_OGRE"><![CDATA[食人魔]]></STRING>
	<STRING key="CARD_SUBTYPE_OOZE"><![CDATA[流浆]]></STRING>
	<STRING key="CARD_SUBTYPE_ORB"><![CDATA[法球]]></STRING>
	<STRING key="CARD_SUBTYPE_ORC"><![CDATA[半兽人]]></STRING>
	<STRING key="CARD_SUBTYPE_ORGG"><![CDATA[欧格]]></STRING>
	<STRING key="CARD_SUBTYPE_OUPHE"><![CDATA[奥夫]]></STRING>
	<STRING key="CARD_SUBTYPE_OX"><![CDATA[牛]]></STRING>
	<STRING key="CARD_SUBTYPE_OYSTER"><![CDATA[牡蛎]]></STRING>
	<STRING key="CARD_SUBTYPE_PEGASUS"><![CDATA[飞马]]></STRING>
	<STRING key="CARD_SUBTYPE_PENTAVITE"><![CDATA[分节]]></STRING>
	<STRING key="CARD_SUBTYPE_PEST"><![CDATA[害虫]]></STRING>
	<STRING key="CARD_SUBTYPE_PHELDDAGRIF"><![CDATA[紫河马]]></STRING>
	<STRING key="CARD_SUBTYPE_PHOENIX"><![CDATA[凤凰]]></STRING>
	<STRING key="CARD_SUBTYPE_PINCHER"><![CDATA[钳手]]></STRING>
	<STRING key="CARD_SUBTYPE_PIRATE"><![CDATA[海盗]]></STRING>
	<STRING key="CARD_SUBTYPE_PLANT"><![CDATA[植物]]></STRING>
	<STRING key="CARD_SUBTYPE_PRAETOR"><![CDATA[魔判官]]></STRING>
	<STRING key="CARD_SUBTYPE_PRISM"><![CDATA[棱镜]]></STRING>
	<STRING key="CARD_SUBTYPE_RABBIT"><![CDATA[兔]]></STRING>
	<STRING key="CARD_SUBTYPE_RANGER"><![CDATA[巡守（无）]]></STRING>
	<STRING key="CARD_SUBTYPE_RAT"><![CDATA[老鼠]]></STRING>
	<STRING key="CARD_SUBTYPE_REBEL"><![CDATA[反抗军]]></STRING>
	<STRING key="CARD_SUBTYPE_REFLECTION"><![CDATA[映影]]></STRING>
	<STRING key="CARD_SUBTYPE_RHINO"><![CDATA[犀牛]]></STRING>
	<STRING key="CARD_SUBTYPE_RIGGER"><![CDATA[整备师]]></STRING>
	<STRING key="CARD_SUBTYPE_ROGUE"><![CDATA[浪客]]></STRING>
	<STRING key="CARD_SUBTYPE_SALAMANDER"><![CDATA[火蜥蜴]]></STRING>
	<STRING key="CARD_SUBTYPE_SAMURAI"><![CDATA[武士]]></STRING>
	<STRING key="CARD_SUBTYPE_SAND"><![CDATA[砂]]></STRING>
	<STRING key="CARD_SUBTYPE_SAPROLING"><![CDATA[腐生物]]></STRING>
	<STRING key="CARD_SUBTYPE_SATYR"><![CDATA[羊蹄人]]></STRING>
	<STRING key="CARD_SUBTYPE_SCARECROW"><![CDATA[稻草人]]></STRING>
	<STRING key="CARD_SUBTYPE_SCORPION"><![CDATA[蝎子]]></STRING>
	<STRING key="CARD_SUBTYPE_SCOUT"><![CDATA[斥候]]></STRING>
	<STRING key="CARD_SUBTYPE_SERF"><![CDATA[农奴]]></STRING>
	<STRING key="CARD_SUBTYPE_SERPENT"><![CDATA[巨蛇]]></STRING>
	<STRING key="CARD_SUBTYPE_SHADE"><![CDATA[阴魂]]></STRING>
	<STRING key="CARD_SUBTYPE_SHAMAN"><![CDATA[祭师]]></STRING>
	<STRING key="CARD_SUBTYPE_SHAPESHIFTER"><![CDATA[变形兽]]></STRING>
	<STRING key="CARD_SUBTYPE_SHEEP"><![CDATA[绵羊]]></STRING>
	<STRING key="CARD_SUBTYPE_SIREN"><![CDATA[塞连]]></STRING>
	<STRING key="CARD_SUBTYPE_SKELETON"><![CDATA[骷髅妖]]></STRING>
	<STRING key="CARD_SUBTYPE_SKITE"><![CDATA[吹牛者（无）]]></STRING>
	<STRING key="CARD_SUBTYPE_SLITH"><![CDATA[斯立兹]]></STRING>
	<STRING key="CARD_SUBTYPE_SLIVER"><![CDATA[裂片妖]]></STRING>
	<STRING key="CARD_SUBTYPE_SLUG"><![CDATA[蛞蝓]]></STRING>
	<STRING key="CARD_SUBTYPE_SNAKE"><![CDATA[蛇]]></STRING>
	<STRING key="CARD_SUBTYPE_SOLDIER"><![CDATA[士兵]]></STRING>
	<STRING key="CARD_SUBTYPE_SOLTARI"><![CDATA[索泰利]]></STRING>
	<STRING key="CARD_SUBTYPE_SPAWN"><![CDATA[后裔]]></STRING>
	<STRING key="CARD_SUBTYPE_SPECTER"><![CDATA[幽灵]]></STRING>
	<STRING key="CARD_SUBTYPE_SPELLSHAPER"><![CDATA[塑法师]]></STRING>
	<STRING key="CARD_SUBTYPE_SPHINX"><![CDATA[史芬斯]]></STRING>
	<STRING key="CARD_SUBTYPE_SPIDER"><![CDATA[蜘蛛]]></STRING>
	<STRING key="CARD_SUBTYPE_SPIKE"><![CDATA[钉兽]]></STRING>
	<STRING key="CARD_SUBTYPE_SPIRIT"><![CDATA[精怪]]></STRING>
	<STRING key="CARD_SUBTYPE_SPLINTER"><![CDATA[碎片]]></STRING>
	<STRING key="CARD_SUBTYPE_SPONGE"><![CDATA[海绵]]></STRING>
	<STRING key="CARD_SUBTYPE_SQUID"><![CDATA[乌贼]]></STRING>
	<STRING key="CARD_SUBTYPE_SQUIRREL"><![CDATA[松鼠]]></STRING>
	<STRING key="CARD_SUBTYPE_STARFISH"><![CDATA[海星]]></STRING>
	<STRING key="CARD_SUBTYPE_SURRAKAR"><![CDATA[苏拉卡]]></STRING>
	<STRING key="CARD_SUBTYPE_SURVIVOR"><![CDATA[幸存者]]></STRING>
	<STRING key="CARD_SUBTYPE_TETRAVITE"><![CDATA[四分节]]></STRING>
	<STRING key="CARD_SUBTYPE_THALAKOS"><![CDATA[萨拉卡斯]]></STRING>
	<STRING key="CARD_SUBTYPE_THOPTER"><![CDATA[振翼机]]></STRING>
	<STRING key="CARD_SUBTYPE_THRULL"><![CDATA[索尔兽]]></STRING>
	<STRING key="CARD_SUBTYPE_TOWNSFOLK"><![CDATA[镇民]]></STRING>
	<STRING key="CARD_SUBTYPE_TRAP"><![CDATA[陷阱]]></STRING>
	<STRING key="CARD_SUBTYPE_TREEFOLK"><![CDATA[树妖]]></STRING>
	<STRING key="CARD_SUBTYPE_TRISKELAVITE"><![CDATA[三分节]]></STRING>
	<STRING key="CARD_SUBTYPE_TROLL"><![CDATA[巨魔]]></STRING>
	<STRING key="CARD_SUBTYPE_TURTLE"><![CDATA[龟]]></STRING>
	<STRING key="CARD_SUBTYPE_UNICORN"><![CDATA[独角兽]]></STRING>
	<STRING key="CARD_SUBTYPE_VAMPIRE"><![CDATA[吸血鬼]]></STRING>
	<STRING key="CARD_SUBTYPE_VEDALKEN"><![CDATA[维多肯]]></STRING>
	<STRING key="CARD_SUBTYPE_VIASHINO"><![CDATA[凡尔西诺]]></STRING>
	<STRING key="CARD_SUBTYPE_VOLVER"><![CDATA[进化体]]></STRING>
	<STRING key="CARD_SUBTYPE_WALL"><![CDATA[墙]]></STRING>
	<STRING key="CARD_SUBTYPE_WARRIOR"><![CDATA[战士]]></STRING>
	<STRING key="CARD_SUBTYPE_WEIRD"><![CDATA[怪奇]]></STRING>
	<STRING key="CARD_SUBTYPE_WEREWOLF"><![CDATA[狼人]]></STRING>
	<STRING key="CARD_SUBTYPE_WHALE"><![CDATA[鲸鱼]]></STRING>
	<STRING key="CARD_SUBTYPE_WIZARD"><![CDATA[法术师]]></STRING>
	<STRING key="CARD_SUBTYPE_WOLF"><![CDATA[狼]]></STRING>
	<STRING key="CARD_SUBTYPE_WOLVERINE"><![CDATA[狼獾]]></STRING>
	<STRING key="CARD_SUBTYPE_WOMBAT"><![CDATA[袋熊]]></STRING>
	<STRING key="CARD_SUBTYPE_WORM"><![CDATA[蠕虫]]></STRING>
	<STRING key="CARD_SUBTYPE_WRAITH"><![CDATA[鬼魂]]></STRING>
	<STRING key="CARD_SUBTYPE_WURM"><![CDATA[亚龙]]></STRING>
	<STRING key="CARD_SUBTYPE_YETI"><![CDATA[雪怪]]></STRING>
	<STRING key="CARD_SUBTYPE_ZOMBIE"><![CDATA[灵俑]]></STRING>
	<STRING key="CARD_SUBTYPE_ZUBERA"><![CDATA[无面鬼]]></STRING>
	<!-- Strings for the Card Sub-Types - Enchantment -->
	<STRING key="CARD_SUBTYPE_AURA"><![CDATA[灵气]]></STRING>
	<STRING key="CARD_SUBTYPE_CURSE"><![CDATA[诅咒]]></STRING>
	<STRING key="CARD_SUBTYPE_SHRINE"><![CDATA[祭祠]]></STRING>
	<!-- Strings for the Card Sub-Types - Land -->
	<STRING key="CARD_SUBTYPE_DESERT"><![CDATA[沙漠]]></STRING>
	<STRING key="CARD_SUBTYPE_FOREST"><![CDATA[树林]]></STRING>
	<STRING key="CARD_SUBTYPE_GATE"><![CDATA[门]]></STRING>
	<STRING key="CARD_SUBTYPE_ISLAND"><![CDATA[海岛]]></STRING>
	<STRING key="CARD_SUBTYPE_LAIR"><![CDATA[巢穴]]></STRING>
	<STRING key="CARD_SUBTYPE_LOCUS"><![CDATA[处所]]></STRING>
	<STRING key="CARD_SUBTYPE_MINE"><![CDATA[矿脉]]></STRING>
	<STRING key="CARD_SUBTYPE_MOUNTAIN"><![CDATA[山脉]]></STRING>
	<STRING key="CARD_SUBTYPE_PLAINS"><![CDATA[平原]]></STRING>
	<STRING key="CARD_SUBTYPE_POWER_PLANT"><![CDATA[动力炉]]></STRING>
	<STRING key="CARD_SUBTYPE_SWAMP"><![CDATA[沼泽]]></STRING>
	<STRING key="CARD_SUBTYPE_TOWER"><![CDATA[塔]]></STRING>
	<STRING key="CARD_SUBTYPE_URZAS"><![CDATA[克撒的]]></STRING>
	<!-- Strings for the Card Sub-Types - Plane -->
	<STRING key="CARD_SUBTYPE_ALARA"><![CDATA[阿拉若]]></STRING>
	<STRING key="CARD_SUBTYPE_AZGOL"><![CDATA[阿兹戈尔]]></STRING>
	<STRING key="CARD_SUBTYPE_BELENON"><![CDATA[贝列侬]]></STRING>
	<STRING key="CARD_SUBTYPE_EQUILOR"><![CDATA[埃奎罗]]></STRING>
	<STRING key="CARD_SUBTYPE_FABACIN"><![CDATA[法巴辛]]></STRING>
	<STRING key="CARD_SUBTYPE_INNISTRAD"><![CDATA[依尼翠]]></STRING>
	<STRING key="CARD_SUBTYPE_KAMIGAWA"><![CDATA[神河]]></STRING>
	<STRING key="CARD_SUBTYPE_KEPHALAI"><![CDATA[凯法莱]]></STRING>
	<STRING key="CARD_SUBTYPE_KOLBAHAN"><![CDATA[寇巴罕]]></STRING>
	<STRING key="CARD_SUBTYPE_KYNETH"><![CDATA[Kyneth]]></STRING>
	<STRING key="CARD_SUBTYPE_LORWYN"><![CDATA[洛温]]></STRING>
	<STRING key="CARD_SUBTYPE_MIRRODIN"><![CDATA[秘罗地]]></STRING>
	<STRING key="CARD_SUBTYPE_MONGSENG"><![CDATA[蒙森]]></STRING>
	<STRING key="CARD_SUBTYPE_NEW_PHYREXIA"><![CDATA[新非瑞克西亚]]></STRING>
	<STRING key="CARD_SUBTYPE_RAVNICA"><![CDATA[拉尼卡]]></STRING>
	<STRING key="CARD_SUBTYPE_REGATHA"><![CDATA[瑞格沙]]></STRING>
	<STRING key="CARD_SUBTYPE_SHANDALAR"><![CDATA[山德拉]]></STRING>
	<STRING key="CARD_SUBTYPE_VRYN"><![CDATA[维林]]></STRING>
	<STRING key="CARD_SUBTYPE_XEREX"><![CDATA[塞里克斯]]></STRING>
	<STRING key="CARD_SUBTYPE_ZENDIKAR"><![CDATA[赞迪卡]]></STRING>
	<!-- Strings for the Card Sub-Types - Planeswalker -->
	<STRING key="CARD_SUBTYPE_AJANI"><![CDATA[阿耶尼]]></STRING>
	<STRING key="CARD_SUBTYPE_BOLAS"><![CDATA[波拉斯]]></STRING>
	<STRING key="CARD_SUBTYPE_CHANDRA"><![CDATA[茜卓]]></STRING>
	<STRING key="CARD_SUBTYPE_ELSPETH"><![CDATA[艾紫培]]></STRING>
	<STRING key="CARD_SUBTYPE_GARRUK"><![CDATA[贾路]]></STRING>
	<STRING key="CARD_SUBTYPE_GIDEON"><![CDATA[基定]]></STRING>
	<STRING key="CARD_SUBTYPE_JACE"><![CDATA[杰斯]]></STRING>
	<STRING key="CARD_SUBTYPE_KARN"><![CDATA[卡恩]]></STRING>
	<STRING key="CARD_SUBTYPE_KOTH"><![CDATA[寇斯]]></STRING>
	<STRING key="CARD_SUBTYPE_LILIANA"><![CDATA[莉莲娜]]></STRING>
	<STRING key="CARD_SUBTYPE_NISSA"><![CDATA[妮莎]]></STRING>
	<STRING key="CARD_SUBTYPE_SARKHAN"><![CDATA[萨坎]]></STRING>
	<STRING key="CARD_SUBTYPE_SORIN"><![CDATA[索霖]]></STRING>
	<STRING key="CARD_SUBTYPE_TEZZERET"><![CDATA[泰兹瑞]]></STRING>
	<STRING key="CARD_SUBTYPE_VENSER"><![CDATA[凡瑟]]></STRING>
	<!-- Strings for the Card Sub-Types - Spell -->
	<STRING key="CARD_SUBTYPE_ARCANE"><![CDATA[古咒]]></STRING>
</LOCALIZATION>